prorch/__init__.py
prorch/dataclasses/orchestrator.py
prorch/dataclasses/pipeline.py
prorch/dataclasses/step.py
prorch/decorators/decorators.py
prorch/exceptions/exceptions.py
prorch/interfaces/repository.py
prorch/mixins/on_continue.py
prorch/mixins/on_start.py
prorch/mixins/provider_manager.py
prorch/mixins/status_manager.py
prorch/orchestrator/orchestrator.py
prorch/pipeline/pipeline.py
prorch/pipeline/services.py
prorch/providers/base_provider.py
prorch/providers/pipeline_provider.py
prorch/providers/step_provider.py
prorch/step/services.py
prorch/step/step.py
prorch/utils/base.py
prorch/utils/constants.py
prorch/utils/services.py
prorch-1.0.1.dist-info/METADATA
prorch-1.0.1.dist-info/WHEEL
prorch-1.0.1.dist-info/top_level.txt
prorch-1.0.1.dist-info/RECORD
