Metadata-Version: 2.1
Name: prorch
Version: 1.0.1
Author: Dani Flores
Author-email: dt.floresc@gmail.com
